absio/__init__.cpython-37m-arm-linux-gnueabihf.so
absio/_funcs.cpython-37m-arm-linux-gnueabihf.so
absio/access.cpython-37m-arm-linux-gnueabihf.so
absio/container.cpython-37m-arm-linux-gnueabihf.so
absio/decorators.cpython-37m-arm-linux-gnueabihf.so
absio/event.cpython-37m-arm-linux-gnueabihf.so
absio/permissions.cpython-37m-arm-linux-gnueabihf.so
absio/user.cpython-37m-arm-linux-gnueabihf.so
absio/utils.cpython-37m-arm-linux-gnueabihf.so
absio/crypto/__init__.cpython-37m-arm-linux-gnueabihf.so
absio/crypto/aes.cpython-37m-arm-linux-gnueabihf.so
absio/crypto/container.cpython-37m-arm-linux-gnueabihf.so
absio/crypto/ecdhe.cpython-37m-arm-linux-gnueabihf.so
absio/crypto/ecdsa.cpython-37m-arm-linux-gnueabihf.so
absio/crypto/hash.cpython-37m-arm-linux-gnueabihf.so
absio/crypto/hmac.cpython-37m-arm-linux-gnueabihf.so
absio/crypto/ies.cpython-37m-arm-linux-gnueabihf.so
absio/crypto/key_file.cpython-37m-arm-linux-gnueabihf.so
absio/crypto/keys.cpython-37m-arm-linux-gnueabihf.so
absio/crypto/p384.cpython-37m-arm-linux-gnueabihf.so
absio/crypto/pbkdf2.cpython-37m-arm-linux-gnueabihf.so
absio/crypto/rkb.cpython-37m-arm-linux-gnueabihf.so
absio/providers/__init__.cpython-37m-arm-linux-gnueabihf.so
absio/providers/ofs/__init__.cpython-37m-arm-linux-gnueabihf.so
absio/providers/ofs/container.cpython-37m-arm-linux-gnueabihf.so
absio/providers/ofs/database.cpython-37m-arm-linux-gnueabihf.so
absio/providers/ofs/key_file.cpython-37m-arm-linux-gnueabihf.so
absio/providers/ofs/keys.cpython-37m-arm-linux-gnueabihf.so
absio/providers/ofs/models.cpython-37m-arm-linux-gnueabihf.so
absio/providers/ofs/ofs_client.cpython-37m-arm-linux-gnueabihf.so
absio/providers/ofs/user.cpython-37m-arm-linux-gnueabihf.so
absio/providers/server/__init__.cpython-37m-arm-linux-gnueabihf.so
absio/providers/server/aws.cpython-37m-arm-linux-gnueabihf.so
absio/providers/server/client.cpython-37m-arm-linux-gnueabihf.so
absio/providers/server/container.cpython-37m-arm-linux-gnueabihf.so
absio-2.6.5.dist-info/LICENSE
absio-2.6.5.dist-info/METADATA
absio-2.6.5.dist-info/WHEEL
absio-2.6.5.dist-info/top_level.txt
absio-2.6.5.dist-info/RECORD
